{"success":true,"message":"OK","data":[{"dex_id":"abcd","name":"ABCDEx","deployer_address":"0x372c7f69d0ecc14f73f89bd8a7dfb41bdf29857c","oracle_updater":"","collateral_asset":"USDC","fee_share_pct":1.0,"is_growth_mode":false,"active_since":"2026-05-11T21:55:11","total_staked_hype":0.0},{"dex_id":"cash","name":"dreamcash","deployer_address":"0xffa8198c62adb1e811629bd54c9b646d726deef7","oracle_updater":"","collateral_asset":"USDC","fee_share_pct":1.0,"is_growth_mode":false,"active_since":"2026-05-11T21:55:11","total_staked_hype":0.0},{"dex_id":"flx","name":"Felix Exchange","deployer_address":"0x2fab552502a6d45920d5741a2f3ebf4c35536352","oracle_updater":"0x94757f8dcb4bf73b850195660e959d1105cfedd5","collateral_asset":"USDC","fee_share_pct":1.0,"is_growth_mode":false,"active_since":"2026-05-11T21:55:11","total_staked_hype":0.0},{"dex_id":"hyna","name":"HyENA","deployer_address":"0x53e655101ea361537124ef814ad4e654b54d0637","oracle_updater":"0xaab93501e78f5105e265a1eafda10ce6530de17e","collateral_asset":"USDC","fee_share_pct":0.11110000312328339,"is_growth_mode":false,"active_since":"2026-05-11T21:55:11","total_staked_hype":0.0},{"dex_id":"km","name":"Markets by Kinetiq","deployer_address":"0x71f0019cc7fa79e4f42587fb7b9a817d8d2429ec","oracle_updater":"","collateral_asset":"USDC","fee_share_pct":1.0,"is_growth_mode":false,"active_since":"2026-05-11T21:55:11","total_staked_hype":0.0},{"dex_id":"para","name":"Paragon","deployer_address":"0x8888888c43cbb7e1c4132542e46831bffd866ed3","oracle_updater":"0x8888888c43cbb7e1c4132542e46831bffd866ed3","collateral_asset":"USDC","fee_share_pct":1.0,"is_growth_mode":false,"active_since":"2026-05-11T21:55:11","total_staked_hype":0.0},{"dex_id":"vntl","name":"Ventuals","deployer_address":"0x8888888192a4a0593c13532ba48449fc24c3beda","oracle_updater":"","collateral_asset":"USDC","fee_share_pct":1.0,"is_growth_mode":false,"active_since":"2026-05-11T21:55:11","total_staked_hype":0.0},{"dex_id":"xyz","name":"XYZ","deployer_address":"0x88806a71d74ad0a510b350545c9ae490912f0888","oracle_updater":"","collateral_asset":"USDC","fee_share_pct":1.0,"is_growth_mode":false,"active_since":"2026-05-11T21:55:11","total_staked_hype":0.0}],"total_count":null,"execution_time_ms":15.15,"next_cursor":null,"has_more":null}