{"status":"live","count":79,"data":[{"outcome_id":0,"coin":"","name":"Recurring","description":"class:priceBinary|underlying:BTC|expiry:20260512-0600|targetPrice:80813|period:1d","class":"priceBinary","underlying":"BTC","expiry":"20260512-0600","target_price":80813.0,"period":"1d","side_specs":"","question_id":null,"quote_token":360,"block_time":"2026-05-11T06:00:09.378958","settled":1,"question_name":"","question_description":"","total_fills":41163,"total_volume":2609243.393579993,"unique_users":1945},{"outcome_id":1,"coin":"#1","name":"Recurring","description":"class:priceBinary|underlying:BTC|expiry:20260504-0600|targetPrice:78213|period:1d","class":"priceBinary","underlying":"BTC","expiry":"20260504-0600","target_price":78213.0,"period":"1d","side_specs":"[{\"name\":\"Yes\"},{\"name\":\"No\"}]","question_id":null,"quote_token":0,"block_time":"2026-05-04T05:59:06.110000","settled":1,"question_name":"","question_description":"","total_fills":31655,"total_volume":3436163.951919963,"unique_users":1202},{"outcome_id":2,"coin":"#2","name":"Recurring","description":"class:priceBinary|underlying:BTC|expiry:20260505-0600|targetPrice:79980|period:1d","class":"priceBinary","underlying":"BTC","expiry":"20260505-0600","target_price":79980.0,"period":"1d","side_specs":"[{\"name\":\"Yes\"},{\"name\":\"No\"}]","question_id":null,"quote_token":0,"block_time":"2026-05-05T06:00:06.695000","settled":1,"question_name":"","question_description":"","total_fills":0,"total_volume":0.0,"unique_users":0},{"outcome_id":3,"coin":"#3","name":"Recurring","description":"class:priceBinary|underlying:BTC|expiry:20260506-0600|targetPrice:80930|period:1d","class":"priceBinary","underlying":"BTC","expiry":"20260506-0600","target_price":80930.0,"period":"1d","side_specs":"[{\"name\":\"Yes\"},{\"name\":\"No\"}]","question_id":null,"quote_token":0,"block_time":"2026-05-06T05:59:06.818000","settled":1,"question_name":"","question_description":"","total_fills":0,"total_volume":0.0,"unique_users":0},{"outcome_id":4,"coin":"#4","name":"Recurring","description":"class:priceBinary|underlying:BTC|expiry:20260507-0600|targetPrice:81287|period:1d","class":"priceBinary","underlying":"BTC","expiry":"20260507-0600","target_price":81287.0,"period":"1d","side_specs":"[{\"name\":\"Yes\"},{\"name\":\"No\"}]","question_id":null,"quote_token":0,"block_time":"2026-05-07T05:59:07.172000","settled":1,"question_name":"","question_description":"","total_fills":0,"total_volume":0.0,"unique_users":0},{"outcome_id":5,"coin":"#5","name":"Recurring","description":"class:priceBinary|underlying:BTC|expiry:20260508-0600|targetPrice:81041|period:1d","class":"priceBinary","underlying":"BTC","expiry":"20260508-0600","target_price":81041.0,"period":"1d","side_specs":"[{\"name\":\"Yes\"},{\"name\":\"No\"}]","question_id":null,"quote_token":0,"block_time":"2026-05-08T06:00:06.252000","settled":1,"question_name":"","question_description":"","total_fills":0,"total_volume":0.0,"unique_users":0},{"outcome_id":6,"coin":"#6","name":"Recurring Fallback","description":"other","class":"","underlying":"","expiry":"","target_price":0.0,"period":"","side_specs":"[{\"name\":\"Yes\"},{\"name\":\"No\"}]","question_id":0,"quote_token":0,"block_time":"2026-05-08T06:00:06.252000","settled":0,"question_name":"Recurring","question_description":"class:priceBucket|underlying:BTC|expiry:20260508-0600|priceThresholds:79303,82540|period:1d","total_fills":0,"total_volume":0.0,"unique_users":0},{"outcome_id":7,"coin":"#7","name":"Recurring Named Outcome","description":"index:0","class":"","underlying":"","expiry":"","target_price":0.0,"period":"","side_specs":"[{\"name\":\"Yes\"},{\"name\":\"No\"}]","question_id":0,"quote_token":0,"block_time":"2026-05-08T06:00:06.252000","settled":0,"question_name":"Recurring","question_description":"class:priceBucket|underlying:BTC|expiry:20260508-0600|priceThresholds:79303,82540|period:1d","total_fills":0,"total_volume":0.0,"unique_users":0},{"outcome_id":8,"coin":"#8","name":"Recurring Named Outcome","description":"index:1","class":"","underlying":"","expiry":"","target_price":0.0,"period":"","side_specs":"[{\"name\":\"Yes\"},{\"name\":\"No\"}]","question_id":0,"quote_token":0,"block_time":"2026-05-08T06:00:06.252000","settled":0,"question_name":"Recurring","question_description":"class:priceBucket|underlying:BTC|expiry:20260508-0600|priceThresholds:79303,82540|period:1d","total_fills":0,"total_volume":0.0,"unique_users":0},{"outcome_id":9,"coin":"#9","name":"Recurring Named Outcome","description":"index:2","class":"","underlying":"","expiry":"","target_price":0.0,"period":"","side_specs":"[{\"name\":\"Yes\"},{\"name\":\"No\"}]","question_id":0,"quote_token":0,"block_time":"2026-05-08T06:00:06.252000","settled":0,"question_name":"Recurring","question_description":"class:priceBucket|underlying:BTC|expiry:20260508-0600|priceThresholds:79303,82540|period:1d","total_fills":0,"total_volume":0.0,"unique_users":0},{"outcome_id":10,"coin":"#10","name":"Recurring","description":"class:priceBinary|underlying:BTC|expiry:20260509-0600|targetPrice:79583|period:1d","class":"priceBinary","underlying":"BTC","expiry":"20260509-0600","target_price":79583.0,"period":"1d","side_specs":"[{\"name\":\"Yes\"},{\"name\":\"No\"}]","question_id":null,"quote_token":0,"block_time":"2026-05-09T05:59:06.633000","settled":1,"question_name":"","question_description":"","total_fills":26527,"total_volume":4713403.472709994,"unique_users":1390},{"outcome_id":11,"coin":"#11","name":"Recurring Fallback","description":"other","class":"","underlying":"","expiry":"","target_price":0.0,"period":"","side_specs":"[{\"name\":\"Yes\"},{\"name\":\"No\"}]","question_id":1,"quote_token":0,"block_time":"2026-05-09T05:59:06.633000","settled":0,"question_name":"Recurring","question_description":"class:priceBucket|underlying:BTC|expiry:20260509-0600|priceThresholds:77991,81174|period:1d","total_fills":22953,"total_volume":906091.7827099947,"unique_users":961},{"outcome_id":12,"coin":"#12","name":"Recurring Named Outcome","description":"index:0","class":"","underlying":"","expiry":"","target_price":0.0,"period":"","side_specs":"[{\"name\":\"Yes\"},{\"name\":\"No\"}]","question_id":1,"quote_token":0,"block_time":"2026-05-09T05:59:06.633000","settled":0,"question_name":"Recurring","question_description":"class:priceBucket|underlying:BTC|expiry:20260509-0600|priceThresholds:77991,81174|period:1d","total_fills":0,"total_volume":0.0,"unique_users":0},{"outcome_id":13,"coin":"#13","name":"Recurring Named Outcome","description":"index:1","class":"","underlying":"","expiry":"","target_price":0.0,"period":"","side_specs":"[{\"name\":\"Yes\"},{\"name\":\"No\"}]","question_id":1,"quote_token":0,"block_time":"2026-05-09T05:59:06.633000","settled":0,"question_name":"Recurring","question_description":"class:priceBucket|underlying:BTC|expiry:20260509-0600|priceThresholds:77991,81174|period:1d","total_fills":0,"total_volume":0.0,"unique_users":0},{"outcome_id":14,"coin":"#14","name":"Recurring Named Outcome","description":"index:2","class":"","underlying":"","expiry":"","target_price":0.0,"period":"","side_specs":"[{\"name\":\"Yes\"},{\"name\":\"No\"}]","question_id":1,"quote_token":0,"block_time":"2026-05-09T05:59:06.633000","settled":0,"question_name":"Recurring","question_description":"class:priceBucket|underlying:BTC|expiry:20260509-0600|priceThresholds:77991,81174|period:1d","total_fills":0,"total_volume":0.0,"unique_users":0},{"outcome_id":15,"coin":"#15","name":"Recurring","description":"class:priceBinary|underlying:BTC|expiry:20260510-0600|targetPrice:80354|period:1d","class":"priceBinary","underlying":"BTC","expiry":"20260510-0600","target_price":80354.0,"period":"1d","side_specs":"[{\"name\":\"Yes\"},{\"name\":\"No\"}]","question_id":null,"quote_token":0,"block_time":"2026-05-10T05:59:06.394000","settled":1,"question_name":"","question_description":"","total_fills":0,"total_volume":0.0,"unique_users":0},{"outcome_id":16,"coin":"#16","name":"Recurring Fallback","description":"other","class":"","underlying":"","expiry":"","target_price":0.0,"period":"","side_specs":"[{\"name\":\"Yes\"},{\"name\":\"No\"}]","question_id":2,"quote_token":0,"block_time":"2026-05-10T06:00:05.964000","settled":0,"question_name":"Recurring","question_description":"class:priceBucket|underlying:BTC|expiry:20260510-0600|priceThresholds:78746,81961|period:1d","total_fills":0,"total_volume":0.0,"unique_users":0},{"outcome_id":17,"coin":"#17","name":"Recurring Named Outcome","description":"index:0","class":"","underlying":"","expiry":"","target_price":0.0,"period":"","side_specs":"[{\"name\":\"Yes\"},{\"name\":\"No\"}]","question_id":2,"quote_token":0,"block_time":"2026-05-10T06:00:05.964000","settled":0,"question_name":"Recurring","question_description":"class:priceBucket|underlying:BTC|expiry:20260510-0600|priceThresholds:78746,81961|period:1d","total_fills":0,"total_volume":0.0,"unique_users":0},{"outcome_id":18,"coin":"#18","name":"Recurring Named Outcome","description":"index:1","class":"","underlying":"","expiry":"","target_price":0.0,"period":"","side_specs":"[{\"name\":\"Yes\"},{\"name\":\"No\"}]","question_id":2,"quote_token":0,"block_time":"2026-05-10T06:00:05.964000","settled":0,"question_name":"Recurring","question_description":"class:priceBucket|underlying:BTC|expiry:20260510-0600|priceThresholds:78746,81961|period:1d","total_fills":0,"total_volume":0.0,"unique_users":0},{"outcome_id":19,"coin":"#19","name":"Recurring Named Outcome","description":"index:2","class":"","underlying":"","expiry":"","target_price":0.0,"period":"","side_specs":"[{\"name\":\"Yes\"},{\"name\":\"No\"}]","question_id":2,"quote_token":0,"block_time":"2026-05-10T06:00:05.964000","settled":0,"question_name":"Recurring","question_description":"class:priceBucket|underlying:BTC|expiry:20260510-0600|priceThresholds:78746,81961|period:1d","total_fills":0,"total_volume":0.0,"unique_users":0},{"outcome_id":20,"coin":"#20","name":"Recurring","description":"class:priceBinary|underlying:BTC|expiry:20260511-0600|targetPrice:80657|period:1d","class":"priceBinary","underlying":"BTC","expiry":"20260511-0600","target_price":80657.0,"period":"1d","side_specs":"[{\"name\":\"Yes\"},{\"name\":\"No\"}]","question_id":null,"quote_token":0,"block_time":"2026-05-11T06:00:06.762000","settled":1,"question_name":"","question_description":"","total_fills":30638,"total_volume":4376944.426020006,"unique_users":1254},{"outcome_id":21,"coin":"#21","name":"Recurring Fallback","description":"other","class":"","underlying":"","expiry":"","target_price":0.0,"period":"","side_specs":"[{\"name\":\"Yes\"},{\"name\":\"No\"}]","question_id":3,"quote_token":0,"block_time":"2026-05-11T06:00:06.762000","settled":0,"question_name":"Recurring","question_description":"class:priceBucket|underlying:BTC|expiry:20260511-0600|priceThresholds:79043,82270|period:1d","total_fills":25026,"total_volume":1298115.253579999,"unique_users":1090},{"outcome_id":22,"coin":"#22","name":"Recurring Named Outcome","description":"index:0","class":"","underlying":"","expiry":"","target_price":0.0,"period":"","side_specs":"[{\"name\":\"Yes\"},{\"name\":\"No\"}]","question_id":3,"quote_token":0,"block_time":"2026-05-11T06:00:06.762000","settled":0,"question_name":"Recurring","question_description":"class:priceBucket|underlying:BTC|expiry:20260511-0600|priceThresholds:79043,82270|period:1d","total_fills":0,"total_volume":0.0,"unique_users":0},{"outcome_id":23,"coin":"#23","name":"Recurring Named Outcome","description":"index:1","class":"","underlying":"","expiry":"","target_price":0.0,"period":"","side_specs":"[{\"name\":\"Yes\"},{\"name\":\"No\"}]","question_id":3,"quote_token":0,"block_time":"2026-05-11T06:00:06.762000","settled":0,"question_name":"Recurring","question_description":"class:priceBucket|underlying:BTC|expiry:20260511-0600|priceThresholds:79043,82270|period:1d","total_fills":0,"total_volume":0.0,"unique_users":0},{"outcome_id":24,"coin":"#24","name":"Recurring Named Outcome","description":"index:2","class":"","underlying":"","expiry":"","target_price":0.0,"period":"","side_specs":"[{\"name\":\"Yes\"},{\"name\":\"No\"}]","question_id":3,"quote_token":0,"block_time":"2026-05-11T06:00:06.762000","settled":0,"question_name":"Recurring","question_description":"class:priceBucket|underlying:BTC|expiry:20260511-0600|priceThresholds:79043,82270|period:1d","total_fills":0,"total_volume":0.0,"unique_users":0},{"outcome_id":25,"coin":"#25","name":"Recurring","description":"class:priceBinary|underlying:BTC|expiry:20260512-0600|targetPrice:80813|period:1d","class":"priceBinary","underlying":"BTC","expiry":"20260512-0600","target_price":80813.0,"period":"1d","side_specs":"[{\"name\":\"Yes\"},{\"name\":\"No\"}]","question_id":null,"quote_token":0,"block_time":"2026-05-11T19:34:06.623000","settled":0,"question_name":"","question_description":"","total_fills":0,"total_volume":0.0,"unique_users":0},{"outcome_id":26,"coin":"#26","name":"Recurring Fallback","description":"other","class":"","underlying":"","expiry":"","target_price":0.0,"period":"","side_specs":"[{\"name\":\"Yes\"},{\"name\":\"No\"}]","question_id":4,"quote_token":0,"block_time":"2026-05-11T19:34:06.623000","settled":0,"question_name":"Recurring","question_description":"class:priceBucket|underlying:BTC|expiry:20260512-0600|priceThresholds:79196,82429|period:1d","total_fills":0,"total_volume":0.0,"unique_users":0},{"outcome_id":27,"coin":"#27","name":"Recurring Named Outcome","description":"index:0","class":"","underlying":"","expiry":"","target_price":0.0,"period":"","side_specs":"[{\"name\":\"Yes\"},{\"name\":\"No\"}]","question_id":4,"quote_token":0,"block_time":"2026-05-11T19:34:06.623000","settled":0,"question_name":"Recurring","question_description":"class:priceBucket|underlying:BTC|expiry:20260512-0600|priceThresholds:79196,82429|period:1d","total_fills":0,"total_volume":0.0,"unique_users":0},{"outcome_id":28,"coin":"#28","name":"Recurring Named Outcome","description":"index:1","class":"","underlying":"","expiry":"","target_price":0.0,"period":"","side_specs":"[{\"name\":\"Yes\"},{\"name\":\"No\"}]","question_id":4,"quote_token":0,"block_time":"2026-05-11T19:34:06.623000","settled":0,"question_name":"Recurring","question_description":"class:priceBucket|underlying:BTC|expiry:20260512-0600|priceThresholds:79196,82429|period:1d","total_fills":0,"total_volume":0.0,"unique_users":0},{"outcome_id":29,"coin":"#29","name":"Recurring Named Outcome","description":"index:2","class":"","underlying":"","expiry":"","target_price":0.0,"period":"","side_specs":"[{\"name\":\"Yes\"},{\"name\":\"No\"}]","question_id":4,"quote_token":0,"block_time":"2026-05-11T19:34:06.623000","settled":0,"question_name":"Recurring","question_description":"class:priceBucket|underlying:BTC|expiry:20260512-0600|priceThresholds:79196,82429|period:1d","total_fills":0,"total_volume":0.0,"unique_users":0},{"outcome_id":30,"coin":"#30","name":"#30","description":"","class":"","underlying":"","expiry":"","target_price":null,"period":"","side_specs":"[]","question_id":null,"quote_token":0,"block_time":"2026-05-05T06:01:06.719000","settled":0,"question_name":"","question_description":"","total_fills":35731,"total_volume":3765911.744219998,"unique_users":1163},{"outcome_id":31,"coin":"#31","name":"#31","description":"","class":"","underlying":"","expiry":"","target_price":null,"period":"","side_specs":"[]","question_id":null,"quote_token":0,"block_time":"2026-05-05T06:01:06.719000","settled":0,"question_name":"","question_description":"","total_fills":29007,"total_volume":1067394.6617400006,"unique_users":868},{"outcome_id":40,"coin":"#40","name":"#40","description":"","class":"","underlying":"","expiry":"","target_price":null,"period":"","side_specs":"[]","question_id":null,"quote_token":0,"block_time":"2026-05-06T06:01:06.814000","settled":0,"question_name":"","question_description":"","total_fills":30258,"total_volume":1198968.4974700038,"unique_users":1032},{"outcome_id":41,"coin":"#41","name":"#41","description":"","class":"","underlying":"","expiry":"","target_price":null,"period":"","side_specs":"[]","question_id":null,"quote_token":0,"block_time":"2026-05-06T06:01:06.814000","settled":0,"question_name":"","question_description":"","total_fills":27894,"total_volume":3018777.2299299943,"unique_users":858},{"outcome_id":50,"coin":"#50","name":"#50","description":"","class":"","underlying":"","expiry":"","target_price":null,"period":"","side_specs":"[]","question_id":null,"quote_token":0,"block_time":"2026-05-07T06:01:06.657000","settled":0,"question_name":"","question_description":"","total_fills":22383,"total_volume":837146.943110002,"unique_users":714},{"outcome_id":51,"coin":"#51","name":"#51","description":"","class":"","underlying":"","expiry":"","target_price":null,"period":"","side_specs":"[]","question_id":null,"quote_token":0,"block_time":"2026-05-07T06:01:06.657000","settled":0,"question_name":"","question_description":"","total_fills":23769,"total_volume":3035689.1792900013,"unique_users":745},{"outcome_id":60,"coin":"#60","name":"#60","description":"","class":"","underlying":"","expiry":"","target_price":null,"period":"","side_specs":"[]","question_id":null,"quote_token":0,"block_time":"2026-05-07T10:22:08.076000","settled":0,"question_name":"","question_description":"","total_fills":671,"total_volume":27752.583128659957,"unique_users":14},{"outcome_id":70,"coin":"#70","name":"#70","description":"","class":"","underlying":"","expiry":"","target_price":null,"period":"","side_specs":"[]","question_id":null,"quote_token":0,"block_time":"2026-05-07T10:19:06.607000","settled":0,"question_name":"","question_description":"","total_fills":3298,"total_volume":69132.05458479,"unique_users":245},{"outcome_id":71,"coin":"#71","name":"#71","description":"","class":"","underlying":"","expiry":"","target_price":null,"period":"","side_specs":"[]","question_id":null,"quote_token":0,"block_time":"2026-05-07T10:19:06.607000","settled":0,"question_name":"","question_description":"","total_fills":1691,"total_volume":147820.56626,"unique_users":115},{"outcome_id":80,"coin":"#80","name":"#80","description":"","class":"","underlying":"","expiry":"","target_price":null,"period":"","side_specs":"[]","question_id":null,"quote_token":0,"block_time":"2026-05-07T10:20:06.638000","settled":0,"question_name":"","question_description":"","total_fills":4109,"total_volume":312279.6273709107,"unique_users":342},{"outcome_id":81,"coin":"#81","name":"#81","description":"","class":"","underlying":"","expiry":"","target_price":null,"period":"","side_specs":"[]","question_id":null,"quote_token":0,"block_time":"2026-05-07T10:20:06.638000","settled":0,"question_name":"","question_description":"","total_fills":2036,"total_volume":57535.09577000011,"unique_users":89},{"outcome_id":90,"coin":"#90","name":"#90","description":"","class":"","underlying":"","expiry":"","target_price":null,"period":"","side_specs":"[]","question_id":null,"quote_token":0,"block_time":"2026-05-07T10:22:08.076000","settled":0,"question_name":"","question_description":"","total_fills":1534,"total_volume":30895.74160161991,"unique_users":126},{"outcome_id":91,"coin":"#91","name":"#91","description":"","class":"","underlying":"","expiry":"","target_price":null,"period":"","side_specs":"[]","question_id":null,"quote_token":0,"block_time":"2026-05-07T10:22:08.076000","settled":0,"question_name":"","question_description":"","total_fills":1091,"total_volume":222024.68877000007,"unique_users":74},{"outcome_id":100,"coin":"#100","name":"#100","description":"","class":"","underlying":"","expiry":"","target_price":null,"period":"","side_specs":"[]","question_id":null,"quote_token":0,"block_time":"2026-05-08T06:01:06.573000","settled":0,"question_name":"","question_description":"","total_fills":29792,"total_volume":1828949.1478000158,"unique_users":668},{"outcome_id":101,"coin":"#101","name":"#101","description":"","class":"","underlying":"","expiry":"","target_price":null,"period":"","side_specs":"[]","question_id":null,"quote_token":0,"block_time":"2026-05-08T06:01:06.573000","settled":0,"question_name":"","question_description":"","total_fills":21129,"total_volume":681097.5848000015,"unique_users":509},{"outcome_id":110,"coin":"#110","name":"#110","description":"","class":"","underlying":"","expiry":"","target_price":null,"period":"","side_specs":"[]","question_id":null,"quote_token":0,"block_time":"2026-05-08T06:01:06.573000","settled":0,"question_name":"","question_description":"","total_fills":570,"total_volume":25033.999817189975,"unique_users":8},{"outcome_id":120,"coin":"#120","name":"#120","description":"","class":"","underlying":"","expiry":"","target_price":null,"period":"","side_specs":"[]","question_id":null,"quote_token":0,"block_time":"2026-05-08T06:01:06.573000","settled":0,"question_name":"","question_description":"","total_fills":1342,"total_volume":32863.68138915,"unique_users":105},{"outcome_id":121,"coin":"#121","name":"#121","description":"","class":"","underlying":"","expiry":"","target_price":null,"period":"","side_specs":"[]","question_id":null,"quote_token":0,"block_time":"2026-05-08T06:01:06.573000","settled":0,"question_name":"","question_description":"","total_fills":961,"total_volume":229701.32641000027,"unique_users":76},{"outcome_id":130,"coin":"#130","name":"#130","description":"","class":"","underlying":"","expiry":"","target_price":null,"period":"","side_specs":"[]","question_id":null,"quote_token":0,"block_time":"2026-05-08T06:01:06.573000","settled":0,"question_name":"","question_description":"","total_fills":2917,"total_volume":452165.4911196011,"unique_users":253},{"outcome_id":131,"coin":"#131","name":"#131","description":"","class":"","underlying":"","expiry":"","target_price":null,"period":"","side_specs":"[]","question_id":null,"quote_token":0,"block_time":"2026-05-08T06:01:06.573000","settled":0,"question_name":"","question_description":"","total_fills":1264,"total_volume":53662.57977999989,"unique_users":61},{"outcome_id":140,"coin":"#140","name":"#140","description":"","class":"","underlying":"","expiry":"","target_price":null,"period":"","side_specs":"[]","question_id":null,"quote_token":0,"block_time":"2026-05-08T06:01:06.573000","settled":0,"question_name":"","question_description":"","total_fills":1889,"total_volume":47905.67700562995,"unique_users":146},{"outcome_id":141,"coin":"#141","name":"#141","description":"","class":"","underlying":"","expiry":"","target_price":null,"period":"","side_specs":"[]","question_id":null,"quote_token":0,"block_time":"2026-05-08T06:01:06.573000","settled":0,"question_name":"","question_description":"","total_fills":1187,"total_volume":230398.2709099999,"unique_users":49},{"outcome_id":150,"coin":"#150","name":"#150","description":"","class":"","underlying":"","expiry":"","target_price":null,"period":"","side_specs":"[]","question_id":null,"quote_token":0,"block_time":"2026-05-09T06:01:06.461000","settled":0,"question_name":"","question_description":"","total_fills":32488,"total_volume":1907298.3127799924,"unique_users":618},{"outcome_id":151,"coin":"#151","name":"#151","description":"","class":"","underlying":"","expiry":"","target_price":null,"period":"","side_specs":"[]","question_id":null,"quote_token":0,"block_time":"2026-05-09T06:01:06.461000","settled":0,"question_name":"","question_description":"","total_fills":27608,"total_volume":750817.2726400023,"unique_users":458},{"outcome_id":160,"coin":"#160","name":"#160","description":"","class":"","underlying":"","expiry":"","target_price":null,"period":"","side_specs":"[]","question_id":null,"quote_token":0,"block_time":"2026-05-09T06:05:06.638000","settled":0,"question_name":"","question_description":"","total_fills":289,"total_volume":19115.916511410014,"unique_users":5},{"outcome_id":170,"coin":"#170","name":"#170","description":"","class":"","underlying":"","expiry":"","target_price":null,"period":"","side_specs":"[]","question_id":null,"quote_token":0,"block_time":"2026-05-09T06:01:06.461000","settled":0,"question_name":"","question_description":"","total_fills":1136,"total_volume":28969.37532992998,"unique_users":78},{"outcome_id":171,"coin":"#171","name":"#171","description":"","class":"","underlying":"","expiry":"","target_price":null,"period":"","side_specs":"[]","question_id":null,"quote_token":0,"block_time":"2026-05-09T06:01:06.461000","settled":0,"question_name":"","question_description":"","total_fills":1143,"total_volume":629891.556680001,"unique_users":63},{"outcome_id":180,"coin":"#180","name":"#180","description":"","class":"","underlying":"","expiry":"","target_price":null,"period":"","side_specs":"[]","question_id":null,"quote_token":0,"block_time":"2026-05-09T06:02:07.163000","settled":0,"question_name":"","question_description":"","total_fills":2845,"total_volume":266646.7393230292,"unique_users":197},{"outcome_id":181,"coin":"#181","name":"#181","description":"","class":"","underlying":"","expiry":"","target_price":null,"period":"","side_specs":"[]","question_id":null,"quote_token":0,"block_time":"2026-05-09T06:02:07.163000","settled":0,"question_name":"","question_description":"","total_fills":1280,"total_volume":44016.55883999993,"unique_users":37},{"outcome_id":190,"coin":"#190","name":"#190","description":"","class":"","underlying":"","expiry":"","target_price":null,"period":"","side_specs":"[]","question_id":null,"quote_token":0,"block_time":"2026-05-09T06:02:07.163000","settled":0,"question_name":"","question_description":"","total_fills":1321,"total_volume":32263.270729860014,"unique_users":96},{"outcome_id":191,"coin":"#191","name":"#191","description":"","class":"","underlying":"","expiry":"","target_price":null,"period":"","side_specs":"[]","question_id":null,"quote_token":0,"block_time":"2026-05-09T06:02:07.163000","settled":0,"question_name":"","question_description":"","total_fills":1120,"total_volume":169102.68048000007,"unique_users":46},{"outcome_id":200,"coin":"#200","name":"#200","description":"","class":"","underlying":"","expiry":"","target_price":null,"period":"","side_specs":"[]","question_id":null,"quote_token":0,"block_time":"2026-05-10T06:01:06.689000","settled":0,"question_name":"","question_description":"","total_fills":68128,"total_volume":5397997.412289989,"unique_users":730},{"outcome_id":201,"coin":"#201","name":"#201","description":"","class":"","underlying":"","expiry":"","target_price":null,"period":"","side_specs":"[]","question_id":null,"quote_token":0,"block_time":"2026-05-10T06:01:06.689000","settled":0,"question_name":"","question_description":"","total_fills":47258,"total_volume":1759651.8410699973,"unique_users":537},{"outcome_id":210,"coin":"#210","name":"#210","description":"","class":"","underlying":"","expiry":"","target_price":null,"period":"","side_specs":"[]","question_id":null,"quote_token":0,"block_time":"2026-05-10T06:01:06.689000","settled":0,"question_name":"","question_description":"","total_fills":286,"total_volume":21463.99980921,"unique_users":4},{"outcome_id":220,"coin":"#220","name":"#220","description":"","class":"","underlying":"","expiry":"","target_price":null,"period":"","side_specs":"[]","question_id":null,"quote_token":0,"block_time":"2026-05-10T06:01:06.689000","settled":0,"question_name":"","question_description":"","total_fills":1094,"total_volume":35563.87662989,"unique_users":78},{"outcome_id":221,"coin":"#221","name":"#221","description":"","class":"","underlying":"","expiry":"","target_price":null,"period":"","side_specs":"[]","question_id":null,"quote_token":0,"block_time":"2026-05-10T06:01:06.689000","settled":0,"question_name":"","question_description":"","total_fills":772,"total_volume":199279.03268,"unique_users":60},{"outcome_id":230,"coin":"#230","name":"#230","description":"","class":"","underlying":"","expiry":"","target_price":null,"period":"","side_specs":"[]","question_id":null,"quote_token":0,"block_time":"2026-05-10T06:01:06.689000","settled":0,"question_name":"","question_description":"","total_fills":4146,"total_volume":446781.8317880309,"unique_users":232},{"outcome_id":231,"coin":"#231","name":"#231","description":"","class":"","underlying":"","expiry":"","target_price":null,"period":"","side_specs":"[]","question_id":null,"quote_token":0,"block_time":"2026-05-10T06:01:06.689000","settled":0,"question_name":"","question_description":"","total_fills":1684,"total_volume":80979.82818000004,"unique_users":44},{"outcome_id":240,"coin":"#240","name":"#240","description":"","class":"","underlying":"","expiry":"","target_price":null,"period":"","side_specs":"[]","question_id":null,"quote_token":0,"block_time":"2026-05-10T06:01:06.689000","settled":0,"question_name":"","question_description":"","total_fills":2264,"total_volume":67083.56569049998,"unique_users":127},{"outcome_id":241,"coin":"#241","name":"#241","description":"","class":"","underlying":"","expiry":"","target_price":null,"period":"","side_specs":"[]","question_id":null,"quote_token":0,"block_time":"2026-05-10T06:03:06.615000","settled":0,"question_name":"","question_description":"","total_fills":1176,"total_volume":126980.61611000032,"unique_users":54},{"outcome_id":250,"coin":"#250","name":"#250","description":"","class":"","underlying":"","expiry":"","target_price":null,"period":"","side_specs":"[]","question_id":null,"quote_token":0,"block_time":"2026-05-11T06:01:06.683000","settled":0,"question_name":"","question_description":"","total_fills":41515,"total_volume":1485571.3579100035,"unique_users":528},{"outcome_id":251,"coin":"#251","name":"#251","description":"","class":"","underlying":"","expiry":"","target_price":null,"period":"","side_specs":"[]","question_id":null,"quote_token":0,"block_time":"2026-05-11T06:01:06.683000","settled":0,"question_name":"","question_description":"","total_fills":24143,"total_volume":786282.7301300023,"unique_users":428},{"outcome_id":260,"coin":"#260","name":"#260","description":"","class":"","underlying":"","expiry":"","target_price":null,"period":"","side_specs":"[]","question_id":null,"quote_token":0,"block_time":"2026-05-11T06:02:05.949000","settled":0,"question_name":"","question_description":"","total_fills":226,"total_volume":14763.499876819997,"unique_users":7},{"outcome_id":270,"coin":"#270","name":"#270","description":"","class":"","underlying":"","expiry":"","target_price":null,"period":"","side_specs":"[]","question_id":null,"quote_token":0,"block_time":"2026-05-11T06:01:06.683000","settled":0,"question_name":"","question_description":"","total_fills":602,"total_volume":20214.197980129997,"unique_users":61},{"outcome_id":271,"coin":"#271","name":"#271","description":"","class":"","underlying":"","expiry":"","target_price":null,"period":"","side_specs":"[]","question_id":null,"quote_token":0,"block_time":"2026-05-11T06:01:06.683000","settled":0,"question_name":"","question_description":"","total_fills":496,"total_volume":54482.888860000035,"unique_users":40},{"outcome_id":280,"coin":"#280","name":"#280","description":"","class":"","underlying":"","expiry":"","target_price":null,"period":"","side_specs":"[]","question_id":null,"quote_token":0,"block_time":"2026-05-11T06:01:06.683000","settled":0,"question_name":"","question_description":"","total_fills":1312,"total_volume":81291.38610779,"unique_users":140},{"outcome_id":281,"coin":"#281","name":"#281","description":"","class":"","underlying":"","expiry":"","target_price":null,"period":"","side_specs":"[]","question_id":null,"quote_token":0,"block_time":"2026-05-11T06:01:06.683000","settled":0,"question_name":"","question_description":"","total_fills":744,"total_volume":44320.79836,"unique_users":39},{"outcome_id":290,"coin":"#290","name":"#290","description":"","class":"","underlying":"","expiry":"","target_price":null,"period":"","side_specs":"[]","question_id":null,"quote_token":0,"block_time":"2026-05-11T06:02:05.949000","settled":0,"question_name":"","question_description":"","total_fills":917,"total_volume":36669.04839572,"unique_users":82},{"outcome_id":291,"coin":"#291","name":"#291","description":"","class":"","underlying":"","expiry":"","target_price":null,"period":"","side_specs":"[]","question_id":null,"quote_token":0,"block_time":"2026-05-11T06:02:05.949000","settled":0,"question_name":"","question_description":"","total_fills":483,"total_volume":26936.25413,"unique_users":31}]}